Metadata-Version: 2.1
Name: template-python-library
Version: 0.0.1
Summary: My package description
Author-email: Anthony Gatti <anthony.a.gatti@gmail.com>
License: MIT License
Project-URL: Homepage, https://github.com/gattia/{my_package}
Project-URL: Documentation, https://anthonygattiphd.com/{my_package}/
Keywords: python
Classifier: Development Status :: 3 - Alpha
Classifier: License :: OSI Approved :: MIT License
Classifier: Topic :: Scientific/Engineering
Classifier: Programming Language :: Python :: 3
Requires-Python: >=3.7
License-File: LICENSE
